LinearProgramOptimizer/__init__.py
LinearProgramOptimizer/revisedSimplex.py
LinearProgramOptimizer-1.0.2.dist-info/METADATA
LinearProgramOptimizer-1.0.2.dist-info/WHEEL
LinearProgramOptimizer-1.0.2.dist-info/top_level.txt
LinearProgramOptimizer-1.0.2.dist-info/RECORD
