Metadata-Version: 2.1
Name: LinearProgramOptimizer
Version: 1.0.2
Summary: Optimization models for solving Linear Programming Problems
Author: OguntolaIbrahim
Author-email: <oibrahimopeyemi@yahoo.com>
Keywords: python,linear programming,operation research,optimization,simplex
Classifier: Development Status :: 2 - Pre-Alpha
Classifier: Intended Audience :: Other Audience
Classifier: Programming Language :: Python :: 3
Classifier: Operating System :: Unix
Classifier: Operating System :: MacOS :: MacOS X
Classifier: Operating System :: Microsoft :: Windows
Requires-Dist: numpy
